ryanair/Dates.py
ryanair/Destinations.py
ryanair/Sample.py
ryanair/__init__.py
ryanair/ryanair.py
ryanair-1.1.dist-info/DESCRIPTION.rst
ryanair-1.1.dist-info/METADATA
ryanair-1.1.dist-info/RECORD
ryanair-1.1.dist-info/WHEEL
ryanair-1.1.dist-info/metadata.json
ryanair-1.1.dist-info/top_level.txt
