Metadata-Version: 2.0
Name: ryanair
Version: 1.1
Summary: Lightweight code to search for (round) flights, using: multiple arrival/departure airports, date range and day of week as input.
Home-page: https://github.com/CR3AL/ryanair
Author: Creal
Author-email: crealcode@gmail.com
License: UNKNOWN
Platform: UNKNOWN
Requires-Dist: datetime
Requires-Dist: pandas (>=0.21)
Requires-Dist: requests
